speckenv.py
speckenv_django.py
speckenv_django_patch.py
speckenv-6.2.dist-info/METADATA
speckenv-6.2.dist-info/WHEEL
speckenv-6.2.dist-info/licenses/LICENSE
speckenv-6.2.dist-info/RECORD
